myLib/__init__.py
LibCode-1.3.0.dist-info/LICENSE
LibCode-1.3.0.dist-info/METADATA
LibCode-1.3.0.dist-info/WHEEL
LibCode-1.3.0.dist-info/top_level.txt
LibCode-1.3.0.dist-info/RECORD
