Metadata-Version: 2.1
Name: LibCode
Version: 1.3.0
Summary: A data structures and algorithms library implemented with Python and tested with Pytest!
Home-page: https://github.com/Axeloooo/LibCode
Author: Axel Sanchez and  Mariia Podgaietska
License: MIT
Classifier: Programming Language :: Python :: 3
Classifier: License :: OSI Approved :: MIT License
Classifier: Operating System :: OS Independent
License-File: LICENSE
Requires-Dist: pytest
